{
  "meta": {
    "index": 2027,
    "hitid": "3VQTAXTYN3FMBEE4NRQL0G7SSWWBUK",
    "workerid": "A1R0Q9CUUBSM5F",
    "probid": "1027A",
    "subid": "44510931"
  },
  "lines": [
    {
      "line": 0,
      "text": "declare ok taking in chars a and b and returning bool",
      "code": "bool ok ( char a , char b )",
      "indent": 0
    },
    {
      "line": 1,
      "text": "if a is equal to b , return true",
      "code": "if ( a == b ) return true ;",
      "indent": 1
    },
    {
      "line": 2,
      "text": "add 1 to a",
      "code": "a ++ ;",
      "indent": 1
    },
    {
      "line": 3,
      "text": "subtract 1 from b",
      "code": "b -- ;",
      "indent": 1
    },
    {
      "line": 4,
      "text": "if a is equal to b , return true",
      "code": "if ( a == b ) return true ;",
      "indent": 1
    },
    {
      "line": 5,
      "text": "set a to a - 1",
      "code": "a -- ;",
      "indent": 1
    },
    {
      "line": 6,
      "text": "set a to a - 1",
      "code": "a -- ;",
      "indent": 1
    },
    {
      "line": 7,
      "text": "add 1 to b",
      "code": "b ++ ;",
      "indent": 1
    },
    {
      "line": 8,
      "text": "increment b",
      "code": "b ++ ;",
      "indent": 1
    },
    {
      "line": 9,
      "text": "if a is b , return true",
      "code": "if ( a == b ) return true ;",
      "indent": 1
    },
    {
      "line": 10,
      "text": "return false",
      "code": "return false ;",
      "indent": 1
    },
    {
      "line": 11,
      "text": "DUMMY",
      "code": "}",
      "indent": 0
    },
    {
      "line": 12,
      "text": "DUMMY",
      "code": "int main() {",
      "indent": 0
    },
    {
      "line": 13,
      "text": "make integer t",
      "code": "int t ;",
      "indent": 1
    },
    {
      "line": 14,
      "text": "read t",
      "code": "cin >> t ;",
      "indent": 1
    },
    {
      "line": 15,
      "text": "for i = 0 to t exclusive",
      "code": "for ( int i = 0 ; i < t ; i ++ )",
      "indent": 1
    },
    {
      "line": 16,
      "text": "make int n",
      "code": "int n ;",
      "indent": 2
    },
    {
      "line": 17,
      "text": "read n",
      "code": "cin >> n ;",
      "indent": 2
    },
    {
      "line": 18,
      "text": "let string s",
      "code": "string s ;",
      "indent": 2
    },
    {
      "line": 19,
      "text": "read s",
      "code": "cin >> s ;",
      "indent": 2
    },
    {
      "line": 20,
      "text": "make bool can = true",
      "code": "bool can = true ;",
      "indent": 2
    },
    {
      "line": 21,
      "text": "for j = 0 to n / 2 exclusive",
      "code": "for ( int j = 0 ; j < n / 2 ; j ++ )",
      "indent": 2
    },
    {
      "line": 22,
      "text": "if ok ( s [ j ] , s [ n - 1 - j ] ) is falsy",
      "code": "if ( ! ok ( s [ j ] , s [ n - 1 - j ] ) )",
      "indent": 3
    },
    {
      "line": 23,
      "text": "set can to false",
      "code": "can = false ;",
      "indent": 4
    },
    {
      "line": 24,
      "text": "break loop",
      "code": "break ;",
      "indent": 4
    },
    {
      "line": 25,
      "text": "DUMMY",
      "code": "}",
      "indent": 3
    },
    {
      "line": 26,
      "text": "DUMMY",
      "code": "}",
      "indent": 2
    },
    {
      "line": 27,
      "text": "if can is truthy",
      "code": "if ( can )",
      "indent": 2
    },
    {
      "line": 28,
      "text": "show \" YES \\ n \"",
      "code": "cout << \" YES\\n \" ;",
      "indent": 3
    },
    {
      "line": 29,
      "text": "otherwise",
      "code": "else",
      "indent": 2
    },
    {
      "line": 30,
      "text": "output \" NO \\ n \"",
      "code": "cout << \" NO\\n \" ;",
      "indent": 3
    },
    {
      "line": 31,
      "text": "DUMMY",
      "code": "}",
      "indent": 1
    },
    {
      "line": 32,
      "text": "DUMMY",
      "code": "}",
      "indent": 0
    }
  ],
  "errors": [
    {
      "mod_line": [
        0
      ],
      "mod_code": [
        "bool ok ( bool a , char b )"
      ],
      "err_line": 5,
      "err_msg": "invalid use of Boolean expression as operand to ‘operator--’"
    },
    {
      "mod_line": [
        5
      ],
      "mod_code": [
        "int a = a - 1 ;"
      ],
      "err_line": 5,
      "err_msg": "declaration of ‘int a’ shadows a parameter"
    },
    {
      "mod_line": [
        6
      ],
      "mod_code": [
        "int a = a - 1 ;"
      ],
      "err_line": 6,
      "err_msg": "declaration of ‘int a’ shadows a parameter"
    },
    {
      "mod_line": [
        14
      ],
      "mod_code": [
        "cin . get ( t ) ;"
      ],
      "err_line": 14,
      "err_msg": "invalid initialization of non-const reference of type ‘std::basic_istream<char>::char_type& {aka char&}’ from an rvalue of type ‘std::basic_istream<char>::char_type {aka char}’"
    },
    {
      "mod_line": [
        15
      ],
      "mod_code": [
        "for ( i = 0 ; i < t ; i ++ )"
      ],
      "err_line": 15,
      "err_msg": "‘i’ was not declared in this scope"
    },
    {
      "mod_line": [
        17
      ],
      "mod_code": [
        "while ( cin >> n )"
      ],
      "err_line": 19,
      "err_msg": "‘s’ was not declared in this scope"
    },
    {
      "mod_line": [
        18
      ],
      "mod_code": [
        "string n ;"
      ],
      "err_line": 18,
      "err_msg": "conflicting declaration ‘std::__cxx11::string n’"
    },
    {
      "mod_line": [
        21
      ],
      "mod_code": [
        "for ( j = 0 ; j < n / 2 ; j ++ )"
      ],
      "err_line": 21,
      "err_msg": "‘j’ was not declared in this scope"
    },
    {
      "mod_line": [
        24
      ],
      "mod_code": [
        "break break ;"
      ],
      "err_line": 24,
      "err_msg": "expected ‘;’ before ‘break’"
    },
    {
      "mod_line": [
        29
      ],
      "mod_code": [
        "otherwise"
      ],
      "err_line": 29,
      "err_msg": "‘otherwise’ was not declared in this scope"
    },
    {
      "mod_line": [
        22,
        21
      ],
      "mod_code": [
        "if ( ok ( s [ j ] , s [ n - 1 - j ] ) )",
        "for ( j = 0 ; j < n / 2 ; j ++ )"
      ],
      "err_line": 21,
      "err_msg": "‘j’ was not declared in this scope"
    },
    {
      "mod_line": [
        22,
        21,
        15
      ],
      "mod_code": [
        "if ( ok ( s [ j ] , s [ n - 1 - j ] ) )",
        "for ( j = 0 ; j < n / 2 ; j ++ )",
        "for ( i = 0 ; i < t ; i ++ )"
      ],
      "err_line": 15,
      "err_msg": "‘i’ was not declared in this scope"
    },
    {
      "mod_line": [
        22,
        21,
        15,
        14
      ],
      "mod_code": [
        "if ( ok ( s [ j ] , s [ n - 1 - j ] ) )",
        "for ( j = 0 ; j < n / 2 ; j ++ )",
        "for ( i = 0 ; i < t ; i ++ )",
        "cin . get ( t ) ;"
      ],
      "err_line": 14,
      "err_msg": "invalid initialization of non-const reference of type ‘std::basic_istream<char>::char_type& {aka char&}’ from an rvalue of type ‘std::basic_istream<char>::char_type {aka char}’"
    },
    {
      "mod_line": [
        22,
        21,
        15,
        5
      ],
      "mod_code": [
        "if ( ok ( s [ j ] , s [ n - 1 - j ] ) )",
        "for ( j = 0 ; j < n / 2 ; j ++ )",
        "for ( i = 0 ; i < t ; i ++ )",
        "int a = a - 1 ;"
      ],
      "err_line": 5,
      "err_msg": "declaration of ‘int a’ shadows a parameter"
    },
    {
      "mod_line": [
        22,
        21,
        15,
        27
      ],
      "mod_code": [
        "if ( ok ( s [ j ] , s [ n - 1 - j ] ) )",
        "for ( j = 0 ; j < n / 2 ; j ++ )",
        "for ( i = 0 ; i < t ; i ++ )",
        "if ( ! can )"
      ],
      "err_line": 15,
      "err_msg": "‘i’ was not declared in this scope"
    },
    {
      "mod_line": [
        22,
        21,
        14
      ],
      "mod_code": [
        "if ( ok ( s [ j ] , s [ n - 1 - j ] ) )",
        "for ( j = 0 ; j < n / 2 ; j ++ )",
        "cin . get ( t ) ;"
      ],
      "err_line": 14,
      "err_msg": "invalid initialization of non-const reference of type ‘std::basic_istream<char>::char_type& {aka char&}’ from an rvalue of type ‘std::basic_istream<char>::char_type {aka char}’"
    },
    {
      "mod_line": [
        22,
        21,
        14,
        5
      ],
      "mod_code": [
        "if ( ok ( s [ j ] , s [ n - 1 - j ] ) )",
        "for ( j = 0 ; j < n / 2 ; j ++ )",
        "cin . get ( t ) ;",
        "int a = a - 1 ;"
      ],
      "err_line": 5,
      "err_msg": "declaration of ‘int a’ shadows a parameter"
    },
    {
      "mod_line": [
        22,
        21,
        14,
        27
      ],
      "mod_code": [
        "if ( ok ( s [ j ] , s [ n - 1 - j ] ) )",
        "for ( j = 0 ; j < n / 2 ; j ++ )",
        "cin . get ( t ) ;",
        "if ( ! can )"
      ],
      "err_line": 14,
      "err_msg": "invalid initialization of non-const reference of type ‘std::basic_istream<char>::char_type& {aka char&}’ from an rvalue of type ‘std::basic_istream<char>::char_type {aka char}’"
    },
    {
      "mod_line": [
        22,
        21,
        5
      ],
      "mod_code": [
        "if ( ok ( s [ j ] , s [ n - 1 - j ] ) )",
        "for ( j = 0 ; j < n / 2 ; j ++ )",
        "int a = a - 1 ;"
      ],
      "err_line": 5,
      "err_msg": "declaration of ‘int a’ shadows a parameter"
    },
    {
      "mod_line": [
        22,
        21,
        5,
        27
      ],
      "mod_code": [
        "if ( ok ( s [ j ] , s [ n - 1 - j ] ) )",
        "for ( j = 0 ; j < n / 2 ; j ++ )",
        "int a = a - 1 ;",
        "if ( ! can )"
      ],
      "err_line": 5,
      "err_msg": "declaration of ‘int a’ shadows a parameter"
    },
    {
      "mod_line": [
        22,
        21,
        27
      ],
      "mod_code": [
        "if ( ok ( s [ j ] , s [ n - 1 - j ] ) )",
        "for ( j = 0 ; j < n / 2 ; j ++ )",
        "if ( ! can )"
      ],
      "err_line": 21,
      "err_msg": "‘j’ was not declared in this scope"
    },
    {
      "mod_line": [
        22,
        15
      ],
      "mod_code": [
        "if ( ok ( s [ j ] , s [ n - 1 - j ] ) )",
        "for ( i = 0 ; i < t ; i ++ )"
      ],
      "err_line": 15,
      "err_msg": "‘i’ was not declared in this scope"
    },
    {
      "mod_line": [
        22,
        15,
        14
      ],
      "mod_code": [
        "if ( ok ( s [ j ] , s [ n - 1 - j ] ) )",
        "for ( i = 0 ; i < t ; i ++ )",
        "cin . get ( t ) ;"
      ],
      "err_line": 14,
      "err_msg": "invalid initialization of non-const reference of type ‘std::basic_istream<char>::char_type& {aka char&}’ from an rvalue of type ‘std::basic_istream<char>::char_type {aka char}’"
    },
    {
      "mod_line": [
        22,
        15,
        14,
        5
      ],
      "mod_code": [
        "if ( ok ( s [ j ] , s [ n - 1 - j ] ) )",
        "for ( i = 0 ; i < t ; i ++ )",
        "cin . get ( t ) ;",
        "int a = a - 1 ;"
      ],
      "err_line": 5,
      "err_msg": "declaration of ‘int a’ shadows a parameter"
    },
    {
      "mod_line": [
        22,
        15,
        14,
        27
      ],
      "mod_code": [
        "if ( ok ( s [ j ] , s [ n - 1 - j ] ) )",
        "for ( i = 0 ; i < t ; i ++ )",
        "cin . get ( t ) ;",
        "if ( ! can )"
      ],
      "err_line": 14,
      "err_msg": "invalid initialization of non-const reference of type ‘std::basic_istream<char>::char_type& {aka char&}’ from an rvalue of type ‘std::basic_istream<char>::char_type {aka char}’"
    },
    {
      "mod_line": [
        22,
        15,
        5
      ],
      "mod_code": [
        "if ( ok ( s [ j ] , s [ n - 1 - j ] ) )",
        "for ( i = 0 ; i < t ; i ++ )",
        "int a = a - 1 ;"
      ],
      "err_line": 5,
      "err_msg": "declaration of ‘int a’ shadows a parameter"
    },
    {
      "mod_line": [
        22,
        15,
        5,
        27
      ],
      "mod_code": [
        "if ( ok ( s [ j ] , s [ n - 1 - j ] ) )",
        "for ( i = 0 ; i < t ; i ++ )",
        "int a = a - 1 ;",
        "if ( ! can )"
      ],
      "err_line": 5,
      "err_msg": "declaration of ‘int a’ shadows a parameter"
    },
    {
      "mod_line": [
        22,
        15,
        27
      ],
      "mod_code": [
        "if ( ok ( s [ j ] , s [ n - 1 - j ] ) )",
        "for ( i = 0 ; i < t ; i ++ )",
        "if ( ! can )"
      ],
      "err_line": 15,
      "err_msg": "‘i’ was not declared in this scope"
    },
    {
      "mod_line": [
        22,
        14
      ],
      "mod_code": [
        "if ( ok ( s [ j ] , s [ n - 1 - j ] ) )",
        "cin . get ( t ) ;"
      ],
      "err_line": 14,
      "err_msg": "invalid initialization of non-const reference of type ‘std::basic_istream<char>::char_type& {aka char&}’ from an rvalue of type ‘std::basic_istream<char>::char_type {aka char}’"
    },
    {
      "mod_line": [
        22,
        14,
        5
      ],
      "mod_code": [
        "if ( ok ( s [ j ] , s [ n - 1 - j ] ) )",
        "cin . get ( t ) ;",
        "int a = a - 1 ;"
      ],
      "err_line": 5,
      "err_msg": "declaration of ‘int a’ shadows a parameter"
    },
    {
      "mod_line": [
        22,
        14,
        5,
        27
      ],
      "mod_code": [
        "if ( ok ( s [ j ] , s [ n - 1 - j ] ) )",
        "cin . get ( t ) ;",
        "int a = a - 1 ;",
        "if ( ! can )"
      ],
      "err_line": 5,
      "err_msg": "declaration of ‘int a’ shadows a parameter"
    },
    {
      "mod_line": [
        22,
        14,
        27
      ],
      "mod_code": [
        "if ( ok ( s [ j ] , s [ n - 1 - j ] ) )",
        "cin . get ( t ) ;",
        "if ( ! can )"
      ],
      "err_line": 14,
      "err_msg": "invalid initialization of non-const reference of type ‘std::basic_istream<char>::char_type& {aka char&}’ from an rvalue of type ‘std::basic_istream<char>::char_type {aka char}’"
    },
    {
      "mod_line": [
        22,
        5
      ],
      "mod_code": [
        "if ( ok ( s [ j ] , s [ n - 1 - j ] ) )",
        "int a = a - 1 ;"
      ],
      "err_line": 5,
      "err_msg": "declaration of ‘int a’ shadows a parameter"
    },
    {
      "mod_line": [
        22,
        5,
        27
      ],
      "mod_code": [
        "if ( ok ( s [ j ] , s [ n - 1 - j ] ) )",
        "int a = a - 1 ;",
        "if ( ! can )"
      ],
      "err_line": 5,
      "err_msg": "declaration of ‘int a’ shadows a parameter"
    },
    {
      "mod_line": [
        21,
        15
      ],
      "mod_code": [
        "for ( j = 0 ; j < n / 2 ; j ++ )",
        "for ( i = 0 ; i < t ; i ++ )"
      ],
      "err_line": 15,
      "err_msg": "‘i’ was not declared in this scope"
    },
    {
      "mod_line": [
        21,
        15,
        14
      ],
      "mod_code": [
        "for ( j = 0 ; j < n / 2 ; j ++ )",
        "for ( i = 0 ; i < t ; i ++ )",
        "cin . get ( t ) ;"
      ],
      "err_line": 14,
      "err_msg": "invalid initialization of non-const reference of type ‘std::basic_istream<char>::char_type& {aka char&}’ from an rvalue of type ‘std::basic_istream<char>::char_type {aka char}’"
    },
    {
      "mod_line": [
        21,
        15,
        14,
        5
      ],
      "mod_code": [
        "for ( j = 0 ; j < n / 2 ; j ++ )",
        "for ( i = 0 ; i < t ; i ++ )",
        "cin . get ( t ) ;",
        "int a = a - 1 ;"
      ],
      "err_line": 5,
      "err_msg": "declaration of ‘int a’ shadows a parameter"
    },
    {
      "mod_line": [
        21,
        15,
        14,
        27
      ],
      "mod_code": [
        "for ( j = 0 ; j < n / 2 ; j ++ )",
        "for ( i = 0 ; i < t ; i ++ )",
        "cin . get ( t ) ;",
        "if ( ! can )"
      ],
      "err_line": 14,
      "err_msg": "invalid initialization of non-const reference of type ‘std::basic_istream<char>::char_type& {aka char&}’ from an rvalue of type ‘std::basic_istream<char>::char_type {aka char}’"
    },
    {
      "mod_line": [
        21,
        15,
        5
      ],
      "mod_code": [
        "for ( j = 0 ; j < n / 2 ; j ++ )",
        "for ( i = 0 ; i < t ; i ++ )",
        "int a = a - 1 ;"
      ],
      "err_line": 5,
      "err_msg": "declaration of ‘int a’ shadows a parameter"
    },
    {
      "mod_line": [
        21,
        15,
        5,
        27
      ],
      "mod_code": [
        "for ( j = 0 ; j < n / 2 ; j ++ )",
        "for ( i = 0 ; i < t ; i ++ )",
        "int a = a - 1 ;",
        "if ( ! can )"
      ],
      "err_line": 5,
      "err_msg": "declaration of ‘int a’ shadows a parameter"
    },
    {
      "mod_line": [
        21,
        15,
        27
      ],
      "mod_code": [
        "for ( j = 0 ; j < n / 2 ; j ++ )",
        "for ( i = 0 ; i < t ; i ++ )",
        "if ( ! can )"
      ],
      "err_line": 15,
      "err_msg": "‘i’ was not declared in this scope"
    },
    {
      "mod_line": [
        21,
        14
      ],
      "mod_code": [
        "for ( j = 0 ; j < n / 2 ; j ++ )",
        "cin . get ( t ) ;"
      ],
      "err_line": 14,
      "err_msg": "invalid initialization of non-const reference of type ‘std::basic_istream<char>::char_type& {aka char&}’ from an rvalue of type ‘std::basic_istream<char>::char_type {aka char}’"
    },
    {
      "mod_line": [
        21,
        14,
        5
      ],
      "mod_code": [
        "for ( j = 0 ; j < n / 2 ; j ++ )",
        "cin . get ( t ) ;",
        "int a = a - 1 ;"
      ],
      "err_line": 5,
      "err_msg": "declaration of ‘int a’ shadows a parameter"
    },
    {
      "mod_line": [
        21,
        14,
        5,
        27
      ],
      "mod_code": [
        "for ( j = 0 ; j < n / 2 ; j ++ )",
        "cin . get ( t ) ;",
        "int a = a - 1 ;",
        "if ( ! can )"
      ],
      "err_line": 5,
      "err_msg": "declaration of ‘int a’ shadows a parameter"
    },
    {
      "mod_line": [
        21,
        14,
        27
      ],
      "mod_code": [
        "for ( j = 0 ; j < n / 2 ; j ++ )",
        "cin . get ( t ) ;",
        "if ( ! can )"
      ],
      "err_line": 14,
      "err_msg": "invalid initialization of non-const reference of type ‘std::basic_istream<char>::char_type& {aka char&}’ from an rvalue of type ‘std::basic_istream<char>::char_type {aka char}’"
    },
    {
      "mod_line": [
        21,
        5
      ],
      "mod_code": [
        "for ( j = 0 ; j < n / 2 ; j ++ )",
        "int a = a - 1 ;"
      ],
      "err_line": 5,
      "err_msg": "declaration of ‘int a’ shadows a parameter"
    },
    {
      "mod_line": [
        21,
        5,
        27
      ],
      "mod_code": [
        "for ( j = 0 ; j < n / 2 ; j ++ )",
        "int a = a - 1 ;",
        "if ( ! can )"
      ],
      "err_line": 5,
      "err_msg": "declaration of ‘int a’ shadows a parameter"
    },
    {
      "mod_line": [
        21,
        27
      ],
      "mod_code": [
        "for ( j = 0 ; j < n / 2 ; j ++ )",
        "if ( ! can )"
      ],
      "err_line": 21,
      "err_msg": "‘j’ was not declared in this scope"
    },
    {
      "mod_line": [
        15,
        14
      ],
      "mod_code": [
        "for ( i = 0 ; i < t ; i ++ )",
        "cin . get ( t ) ;"
      ],
      "err_line": 14,
      "err_msg": "invalid initialization of non-const reference of type ‘std::basic_istream<char>::char_type& {aka char&}’ from an rvalue of type ‘std::basic_istream<char>::char_type {aka char}’"
    },
    {
      "mod_line": [
        15,
        14,
        5
      ],
      "mod_code": [
        "for ( i = 0 ; i < t ; i ++ )",
        "cin . get ( t ) ;",
        "int a = a - 1 ;"
      ],
      "err_line": 5,
      "err_msg": "declaration of ‘int a’ shadows a parameter"
    },
    {
      "mod_line": [
        15,
        14,
        5,
        27
      ],
      "mod_code": [
        "for ( i = 0 ; i < t ; i ++ )",
        "cin . get ( t ) ;",
        "int a = a - 1 ;",
        "if ( ! can )"
      ],
      "err_line": 5,
      "err_msg": "declaration of ‘int a’ shadows a parameter"
    },
    {
      "mod_line": [
        15,
        14,
        27
      ],
      "mod_code": [
        "for ( i = 0 ; i < t ; i ++ )",
        "cin . get ( t ) ;",
        "if ( ! can )"
      ],
      "err_line": 14,
      "err_msg": "invalid initialization of non-const reference of type ‘std::basic_istream<char>::char_type& {aka char&}’ from an rvalue of type ‘std::basic_istream<char>::char_type {aka char}’"
    },
    {
      "mod_line": [
        15,
        5
      ],
      "mod_code": [
        "for ( i = 0 ; i < t ; i ++ )",
        "int a = a - 1 ;"
      ],
      "err_line": 5,
      "err_msg": "declaration of ‘int a’ shadows a parameter"
    },
    {
      "mod_line": [
        15,
        5,
        27
      ],
      "mod_code": [
        "for ( i = 0 ; i < t ; i ++ )",
        "int a = a - 1 ;",
        "if ( ! can )"
      ],
      "err_line": 5,
      "err_msg": "declaration of ‘int a’ shadows a parameter"
    },
    {
      "mod_line": [
        15,
        27
      ],
      "mod_code": [
        "for ( i = 0 ; i < t ; i ++ )",
        "if ( ! can )"
      ],
      "err_line": 15,
      "err_msg": "‘i’ was not declared in this scope"
    },
    {
      "mod_line": [
        14,
        5
      ],
      "mod_code": [
        "cin . get ( t ) ;",
        "int a = a - 1 ;"
      ],
      "err_line": 5,
      "err_msg": "declaration of ‘int a’ shadows a parameter"
    },
    {
      "mod_line": [
        14,
        5,
        27
      ],
      "mod_code": [
        "cin . get ( t ) ;",
        "int a = a - 1 ;",
        "if ( ! can )"
      ],
      "err_line": 5,
      "err_msg": "declaration of ‘int a’ shadows a parameter"
    },
    {
      "mod_line": [
        14,
        27
      ],
      "mod_code": [
        "cin . get ( t ) ;",
        "if ( ! can )"
      ],
      "err_line": 14,
      "err_msg": "invalid initialization of non-const reference of type ‘std::basic_istream<char>::char_type& {aka char&}’ from an rvalue of type ‘std::basic_istream<char>::char_type {aka char}’"
    },
    {
      "mod_line": [
        5,
        27
      ],
      "mod_code": [
        "int a = a - 1 ;",
        "if ( ! can )"
      ],
      "err_line": 5,
      "err_msg": "declaration of ‘int a’ shadows a parameter"
    }
  ]
}