{
  "meta": {
    "index": 841,
    "hitid": "32CAVSKPCEJLYGWCLUXWU4UJ6KZU1E",
    "workerid": "A1AYVATMT88U1W",
    "probid": "267A",
    "subid": "45372818"
  },
  "lines": [
    {
      "line": 0,
      "text": "DUMMY",
      "code": "int main() {",
      "indent": 0
    },
    {
      "line": 1,
      "text": "let n , a , b , res be long integers",
      "code": "long long n , a , b , res ;",
      "indent": 1
    },
    {
      "line": 2,
      "text": "read n",
      "code": "cin >> n ;",
      "indent": 1
    },
    {
      "line": 3,
      "text": "for long integer i = 1 to n inclusive",
      "code": "for ( long long i = 1 ; i <= n ; i ++ )",
      "indent": 1
    },
    {
      "line": 4,
      "text": "res is equal to 0",
      "code": "res = 0 ;",
      "indent": 2
    },
    {
      "line": 5,
      "text": "read a , b",
      "code": "cin >> a >> b ;",
      "indent": 2
    },
    {
      "line": 6,
      "text": "while a is greater than 0 and b is greater than 0",
      "code": "while ( a > 0 && b > 0 )",
      "indent": 2
    },
    {
      "line": 7,
      "text": "if a is less than b , swap the values a , b",
      "code": "if ( a < b ) swap ( a , b ) ;",
      "indent": 3
    },
    {
      "line": 8,
      "text": "increment res by a / b",
      "code": "res = res + a / b ;",
      "indent": 3
    },
    {
      "line": 9,
      "text": "a is equal to a modulo b",
      "code": "a = a % b ;",
      "indent": 3
    },
    {
      "line": 10,
      "text": "DUMMY",
      "code": "}",
      "indent": 2
    },
    {
      "line": 11,
      "text": "print res and newline",
      "code": "cout << res << endl ;",
      "indent": 2
    },
    {
      "line": 12,
      "text": "DUMMY",
      "code": "}",
      "indent": 1
    },
    {
      "line": 13,
      "text": "DUMMY",
      "code": "return 0;",
      "indent": 1
    },
    {
      "line": 14,
      "text": "DUMMY",
      "code": "}",
      "indent": 0
    }
  ],
  "errors": []
}