{
  "meta": {
    "index": 1897,
    "hitid": "3S37Y8CWI8UFIJI03CVZAQMJ3KO4W4",
    "workerid": "A1C6BNLZXBOMT7",
    "probid": "460A",
    "subid": "48913769"
  },
  "lines": [
    {
      "line": 0,
      "text": "DUMMY",
      "code": "int main() {",
      "indent": 0
    },
    {
      "line": 1,
      "text": "a , b , hari , hitung = integers with hari = 1 , hitung = 0",
      "code": "int a , b , hari = 1 , hitung = 0 ;",
      "indent": 1
    },
    {
      "line": 2,
      "text": "Read a , b",
      "code": "cin >> a >> b ;",
      "indent": 1
    },
    {
      "line": 3,
      "text": "while a is not equal to 0",
      "code": "while ( a != 0 )",
      "indent": 1
    },
    {
      "line": 4,
      "text": "decrement a",
      "code": "a -- ;",
      "indent": 2
    },
    {
      "line": 5,
      "text": "increment hitung",
      "code": "hitung ++ ;",
      "indent": 2
    },
    {
      "line": 6,
      "text": "if hari modulo b is 0 , then increment a",
      "code": "if ( hari % b == 0 ) { a ++ ; }",
      "indent": 2
    },
    {
      "line": 7,
      "text": "increment hari",
      "code": "hari ++ ;",
      "indent": 2
    },
    {
      "line": 8,
      "text": "DUMMY",
      "code": "}",
      "indent": 1
    },
    {
      "line": 9,
      "text": "print hari - 1 and a new line",
      "code": "cout << hari - 1 << endl ;",
      "indent": 1
    },
    {
      "line": 10,
      "text": "DUMMY",
      "code": "}",
      "indent": 0
    }
  ],
  "errors": []
}